unicorn_fy-1.14.1.dist-info/RECORD
unicorn_fy-1.14.1.dist-info/WHEEL
unicorn_fy-1.14.1.dist-info/METADATA
unicorn_fy-1.14.1.dist-info/top_level.txt
unicorn_fy-1.14.1.dist-info/LICENSE
unicorn_fy/unicorn_fy.cpython-312-i386-linux-musl.so
unicorn_fy/__init__.cpython-312-i386-linux-musl.so
