Metadata-Version: 2.1
Name: unicorn-fy
Version: 1.14.1
Summary: A Python API by LUCIT to convert received raw data from crypto exchange API endpoints into well-formed python dictionaries.
Home-page: https://github.com/LUCIT-Systems-and-Development/unicorn-fy
Author: LUCIT Systems and Development
Author-email: info@lucit.tech
License: LSOSL - LUCIT Synergetic Open Source License
Project-URL: Documentation, https://unicorn-fy.docs.lucit.tech
Project-URL: Wiki, https://github.com/LUCIT-Systems-and-Development/unicorn-fy/wiki
Project-URL: Author, https://www.lucit.tech
Project-URL: Changes, https://unicorn-fy.docs.lucit.tech/changelog.html
Project-URL: License, https://unicorn-fy.docs.lucit.tech/license.html
Project-URL: Issue Tracker, https://github.com/LUCIT-Systems-and-Development/unicorn-fy/issues
Project-URL: Chat, https://gitter.im/unicorn-binance-suite/unicorn-fy
Project-URL: Telegram, https://t.me/unicorndevs
Project-URL: Get Support, https://www.lucit.tech/get-support.html
Keywords: binance,api,exchange,unify,binance-dex,binance-chain,rest-api,websockets
Classifier: Development Status :: 5 - Production/Stable
Classifier: Programming Language :: Python :: 3.7
Classifier: Programming Language :: Python :: 3.8
Classifier: Programming Language :: Python :: 3.9
Classifier: Programming Language :: Python :: 3.10
Classifier: Programming Language :: Python :: 3.11
Classifier: Programming Language :: Python :: 3.12
Classifier: License :: OSI Approved :: MIT License
Classifier: Intended Audience :: Developers
Classifier: Intended Audience :: Financial and Insurance Industry
Classifier: Intended Audience :: Information Technology
Classifier: Intended Audience :: Science/Research
Classifier: Operating System :: OS Independent
Classifier: Topic :: Office/Business :: Financial :: Investment
Classifier: Topic :: Software Development :: Libraries :: Python Modules
Requires-Python: >=3.7.0
License-File: LICENSE
Requires-Dist: ujson
Requires-Dist: requests
Requires-Dist: Cython
